owiener.py
owiener-1.0.9.dist-info/LICENSE
owiener-1.0.9.dist-info/METADATA
owiener-1.0.9.dist-info/WHEEL
owiener-1.0.9.dist-info/top_level.txt
owiener-1.0.9.dist-info/RECORD
