Metadata-Version: 2.1
Name: owiener
Version: 1.0.9
Summary: A Python3 implementation of the Wiener attack on RSA
Author-email: Nao Yonashiro <owan.orisano@gmail.com>
License: MIT License
Project-URL: Repository, https://github.com/orisano/owiener
Classifier: Development Status :: 5 - Production/Stable
Classifier: Topic :: Security :: Cryptography
Classifier: License :: OSI Approved :: MIT License
Classifier: Programming Language :: Python :: 3.5
Classifier: Programming Language :: Python :: 3.6
Classifier: Programming Language :: Python :: 3.7
Classifier: Programming Language :: Python :: 3.8
Classifier: Programming Language :: Python :: 3.9
Classifier: Programming Language :: Python :: 3.10
Classifier: Programming Language :: Python :: 3.11
Classifier: Programming Language :: Python :: 3.12
Classifier: Programming Language :: Python :: 3 :: Only
Requires-Python: >=3.5
License-File: LICENSE
